{
  "EventType": "comment_created",
  "Provider": "bitbucket",
  "Timestamp": "",
  "Repository": {
    "ID": "{352533c2-42e6-4035-9beb-57035eeedd12}",
    "Name": "fb_backends",
    "FullName": "contorted/fb_backends",
    "WebURL": "https://bitbucket.org/contorted/fb_backends",
    "CloneURL": "",
    "DefaultBranch": "",
    "Owner": {
      "ID": "",
      "Username": "contorted",
      "Name": "contorted",
      "Email": "",
      "AvatarURL": "",
      "WebURL": "",
      "Metadata": {
        "account_id": "",
        "type": "team",
        "uuid": "{40dafde9-4408-4e0b-af0a-335aec19f860}"
      }
    },
    "Metadata": {
      "type": "repository"
    }
  },
  "MergeRequest": null,
  "Comment": {
    "ID": "699609085",
    "Body": "@{712020:cd5db0f9-0d82-428a-b778-80a5b9416408} can you give an example of the right kind of return value?",
    "Author": {
      "ID": "712020:a02bc964-a339-4d21-baa3-71da9c43382e",
      "Username": "",
      "Name": "Contorted Expression",
      "Email": "",
      "AvatarURL": "",
      "WebURL": "",
      "Metadata": {
        "account_id": "712020:a02bc964-a339-4d21-baa3-71da9c43382e",
        "type": "user",
        "uuid": "{225d8b60-7756-4d30-ba43-f71d844bf97e}"
      }
    },
    "CreatedAt": "2025-10-14T10:59:07.311957+00:00",
    "UpdatedAt": "2025-10-14T10:59:07.322090+00:00",
    "WebURL": "https://bitbucket.org/contorted/fb_backends/pull-requests/1/_/diff#comment-699609085",
    "InReplyToID": "699606563",
    "Position": {
      "FilePath": "activepm2.py",
      "LineNumber": 189,
      "LineType": "new",
      "StartLine": null,
      "EndLine": null,
      "Metadata": null
    },
    "DiscussionID": null,
    "System": false,
    "Metadata": {
      "account_id": "712020:a02bc964-a339-4d21-baa3-71da9c43382e",
      "comment_type": "pullrequest_comment",
      "pr_number": 1,
      "pr_title": "p1 test",
      "pr_url": "https://bitbucket.org/contorted/fb_backends/pull-requests/1",
      "provider": "bitbucket",
      "repository": "fb_backends",
      "user_uuid": "{225d8b60-7756-4d30-ba43-f71d844bf97e}",
      "workspace": "contorted"
    }
  },
  "ReviewerChange": null,
  "Actor": {
    "ID": "712020:a02bc964-a339-4d21-baa3-71da9c43382e",
    "Username": "",
    "Name": "Contorted Expression",
    "Email": "",
    "AvatarURL": "",
    "WebURL": "",
    "Metadata": {
      "account_id": "712020:a02bc964-a339-4d21-baa3-71da9c43382e",
      "type": "user",
      "uuid": "{225d8b60-7756-4d30-ba43-f71d844bf97e}"
    }
  }
}